aiotrino/__init__.py
aiotrino/_version.py
aiotrino/auth.py
aiotrino/client.py
aiotrino/constants.py
aiotrino/dbapi.py
aiotrino/exceptions.py
aiotrino/logging.py
aiotrino/mapper.py
aiotrino/transaction.py
aiotrino/types.py
aiotrino/utils.py
aiotrino/sqlalchemy/__init__.py
aiotrino/sqlalchemy/compiler.py
aiotrino/sqlalchemy/datatype.py
aiotrino/sqlalchemy/dialect.py
aiotrino/sqlalchemy/error.py
aiotrino/sqlalchemy/util.py
aiotrino-0.3.0.dist-info/LICENSE
aiotrino-0.3.0.dist-info/METADATA
aiotrino-0.3.0.dist-info/WHEEL
aiotrino-0.3.0.dist-info/entry_points.txt
aiotrino-0.3.0.dist-info/top_level.txt
aiotrino-0.3.0.dist-info/RECORD
