Metadata-Version: 2.2
Name: aiotrino
Version: 0.3.0
Summary: Asyncio client for the Trino distributed SQL Engine
Home-page: https://github.com/mvanderlee/aiotrino
Author: Michiel van der Lee & Trino Team
Author-email: jmt.vanderlee@gmail.com
License: Apache 2.0
Classifier: Development Status :: 4 - Beta
Classifier: Intended Audience :: Developers
Classifier: License :: OSI Approved :: Apache Software License
Classifier: Operating System :: MacOS :: MacOS X
Classifier: Operating System :: POSIX
Classifier: Operating System :: Microsoft :: Windows
Classifier: Programming Language :: Python
Classifier: Programming Language :: Python :: 3
Classifier: Programming Language :: Python :: 3.9
Classifier: Programming Language :: Python :: 3.10
Classifier: Programming Language :: Python :: 3.11
Classifier: Programming Language :: Python :: 3.12
Classifier: Programming Language :: Python :: 3.13
Classifier: Programming Language :: Python :: Implementation :: CPython
Classifier: Programming Language :: Python :: Implementation :: PyPy
Classifier: Topic :: Database :: Front-Ends
Requires-Python: >=3.9
License-File: LICENSE
Requires-Dist: aioitertools
Requires-Dist: lz4
Requires-Dist: python-dateutil
Requires-Dist: pytz
Requires-Dist: aiohttp
Requires-Dist: tzdata
Requires-Dist: tzlocal
Requires-Dist: zstandard
Provides-Extra: all
Requires-Dist: sqlalchemy>=1.4; extra == "all"
Provides-Extra: sqlalchemy
Requires-Dist: sqlalchemy>=1.4; extra == "sqlalchemy"
Provides-Extra: tests
Requires-Dist: sqlalchemy>=1.4; extra == "tests"
Requires-Dist: httpretty<1.1; extra == "tests"
Requires-Dist: mocket[speedups]; extra == "tests"
Requires-Dist: pytest; extra == "tests"
Requires-Dist: pytest-aiohttp; extra == "tests"
Requires-Dist: pytest-asyncio; extra == "tests"
Requires-Dist: pytest-runner; extra == "tests"
Requires-Dist: aioresponses; extra == "tests"
Requires-Dist: mock; extra == "tests"
Requires-Dist: pytz; extra == "tests"
Requires-Dist: pre-commit; extra == "tests"
Requires-Dist: ruff; extra == "tests"
Requires-Dist: isort; extra == "tests"
Requires-Dist: testcontainers; extra == "tests"
Requires-Dist: boto3; extra == "tests"
Dynamic: author
Dynamic: author-email
Dynamic: classifier
Dynamic: description
Dynamic: description-content-type
Dynamic: home-page
Dynamic: license
Dynamic: provides-extra
Dynamic: requires-dist
Dynamic: requires-python
Dynamic: summary
